pyaudiosynth/__init__.py
pyaudiosynth/note.py
pyaudiosynth/synthesizer.py
pyaudiosynth/wave.py
pyaudiosynth-0.2.5.dist-info/METADATA
pyaudiosynth-0.2.5.dist-info/WHEEL
pyaudiosynth-0.2.5.dist-info/entry_points.txt
pyaudiosynth-0.2.5.dist-info/licenses/LICENSE
pyaudiosynth-0.2.5.dist-info/RECORD
